mcpf_db/pg/__init__.py
mcpf_db/pg/helper.py
mcpf_db_postgres-0.1.0.dist-info/LICENSE
mcpf_db_postgres-0.1.0.dist-info/METADATA
mcpf_db_postgres-0.1.0.dist-info/WHEEL
mcpf_db_postgres-0.1.0.dist-info/RECORD
